mkdocs_autozip/__init__.py
mkdocs_autozip/autozip.py
mkdocs_autozip-0.2.1.dist-info/LICENSE.md
mkdocs_autozip-0.2.1.dist-info/METADATA
mkdocs_autozip-0.2.1.dist-info/WHEEL
mkdocs_autozip-0.2.1.dist-info/entry_points.txt
mkdocs_autozip-0.2.1.dist-info/top_level.txt
mkdocs_autozip-0.2.1.dist-info/RECORD
