Metadata-Version: 2.1
Name: mkdocs-autozip
Version: 0.2.1
Summary: A mkdocs plugin for zipping source files during build.
Home-page: https://github.com/martinohanlon/mkdocs_autozip
Author: Martin O'Hanlon
Author-email: martin.ohanlon@raspberrypi.org
Keywords: mkdocs,zip,plugin
Classifier: Development Status :: 4 - Beta
Classifier: Intended Audience :: Developers
Classifier: Topic :: Education
Classifier: License :: OSI Approved :: MIT License
Classifier: Programming Language :: Python :: 3
Classifier: Programming Language :: Python :: 3.5
Classifier: Programming Language :: Python :: 3.6
Classifier: Programming Language :: Python :: 3.7
Classifier: Programming Language :: Python :: 3.8
License-File: LICENSE.md
Requires-Dist: mkdocs
Requires-Dist: requests
